{
  "project": {
    "slug": "icon-bay-fit-out",
    "code": "ICON-BAY-F",
    "name": "ICON BAY Fit-Out",
    "contractor": "CYFR FITOUT L.L.C",
    "customer": "Huseyn Gasimov",
    "location": "Дубай, ОАЭ",
    "contractDate": "2026-06-02",
    "currency": "AED",
    "vatRate": 0.05,
    "totalExVat": 373000,
    "totalIncVat": 391650,
    "startDate": "2026-07-21",
    "endDate": "2026-11-05",
    "durationDays": 108,
    "contractEndDate": "2026-11-05",
    "lastUpdated": "2026-07-21T13:33:56.231Z",
    "lastUpdatedBy": "Sergei (contracts import)",
    "paymentStages": [
      {
        "id": "P1",
        "label": "Аванс",
        "share": 0.15,
        "note": "Мобилизация и проектная поддержка"
      },
      {
        "id": "P2",
        "label": "Этап 1",
        "share": 0.4,
        "note": "Черновые работы и first-fix"
      },
      {
        "id": "P3",
        "label": "Этап 2",
        "share": 0.35,
        "note": "Чистовая отделка и final-fix"
      },
      {
        "id": "P4",
        "label": "Этап 3",
        "share": 0.1,
        "note": "Устранение замечаний и сдача"
      }
    ]
  },
  "sections": [
    {
      "id": "demolition",
      "name": "Демонтаж",
      "color": "#64748b"
    },
    {
      "id": "plumbing",
      "name": "Сантехника",
      "color": "#3b82f6",
      "sub": true
    },
    {
      "id": "electrical",
      "name": "Электрика",
      "color": "#eab308",
      "sub": true
    },
    {
      "id": "flooring",
      "name": "Полы",
      "color": "#f97316"
    },
    {
      "id": "drywall",
      "name": "Гипсокартонные работы",
      "color": "#ec4899"
    },
    {
      "id": "finishing",
      "name": "Штукатурно-малярные",
      "color": "#a855f7"
    },
    {
      "id": "furniture",
      "name": "Мебель и декор",
      "color": "#475569"
    },
    {
      "id": "cleaning",
      "name": "Уборка",
      "color": "#84cc16"
    },
    {
      "id": "materials",
      "name": "Логистика и материалы",
      "color": "#d4a017"
    }
  ],
  "stages": [
    {
      "id": "ST1",
      "name": "Этап 1 · Черновые (демонтаж, MEP)",
      "color": "#1e3b60"
    },
    {
      "id": "ST2",
      "name": "Этап 2 · Конструкции (ГКЛ, полы)",
      "color": "#2d6a8f"
    },
    {
      "id": "ST3",
      "name": "Этап 3 · Чистовые (отделка)",
      "color": "#c9a96e"
    },
    {
      "id": "ST4",
      "name": "Этап 4 · Сдача (мебель, уборка)",
      "color": "#8a5a44"
    }
  ],
  "milestones": [],
  "holidays": [],
  "tasks": [
    {
      "id": "1",
      "section": "demolition",
      "stage": "ST1",
      "name": "Демонтажные работы",
      "qty": null,
      "unit": "",
      "costIncVat": 16697.75,
      "durationDaysPlanned": 10,
      "planStart": "2026-07-21",
      "planEnd": "2026-07-30",
      "actualStart": null,
      "actualEnd": null
    },
    {
      "id": "2",
      "section": "finishing",
      "stage": "ST2",
      "name": "Отделка и покраска стен",
      "qty": null,
      "unit": "",
      "costIncVat": 46652.66,
      "durationDaysPlanned": 14,
      "planStart": "2026-07-31",
      "planEnd": "2026-08-13",
      "actualStart": null,
      "actualEnd": null
    },
    {
      "id": "3",
      "section": "drywall",
      "stage": "ST2",
      "name": "Установка потолков из ГКЛ",
      "qty": null,
      "unit": "",
      "costIncVat": 30220.38,
      "durationDaysPlanned": 10,
      "planStart": "2026-08-14",
      "planEnd": "2026-08-23",
      "actualStart": null,
      "actualEnd": null
    },
    {
      "id": "4",
      "section": "flooring",
      "stage": "ST2",
      "name": "Укладка плитки и отделка санузлов",
      "qty": null,
      "unit": "",
      "costIncVat": 17073.22,
      "durationDaysPlanned": 10,
      "planStart": "2026-08-24",
      "planEnd": "2026-09-02",
      "actualStart": null,
      "actualEnd": null
    },
    {
      "id": "5",
      "section": "electrical",
      "stage": "ST2",
      "name": "Электромонтажные работы",
      "qty": null,
      "unit": "",
      "costIncVat": 55180.87,
      "durationDaysPlanned": 20,
      "planStart": "2026-09-03",
      "planEnd": "2026-09-22",
      "actualStart": null,
      "actualEnd": null
    },
    {
      "id": "6",
      "section": "plumbing",
      "stage": "ST2",
      "name": "Сантехнические работы",
      "qty": null,
      "unit": "",
      "costIncVat": 12229.82,
      "durationDaysPlanned": 15,
      "planStart": "2026-09-23",
      "planEnd": "2026-10-07",
      "actualStart": null,
      "actualEnd": null
    },
    {
      "id": "7",
      "section": "finishing",
      "stage": "ST3",
      "name": "Чистовая отделка",
      "qty": null,
      "unit": "",
      "costIncVat": 57932.88,
      "durationDaysPlanned": 14,
      "planStart": "2026-10-08",
      "planEnd": "2026-10-21",
      "actualStart": null,
      "actualEnd": null
    },
    {
      "id": "8",
      "section": "materials",
      "stage": "ST3",
      "name": "Прочие работы по контракту",
      "qty": null,
      "unit": "",
      "costIncVat": 140521.76,
      "durationDaysPlanned": 7,
      "planStart": "2026-10-22",
      "planEnd": "2026-10-28",
      "actualStart": null,
      "actualEnd": null
    },
    {
      "id": "9",
      "section": "furniture",
      "stage": "ST4",
      "name": "Установка дверей и мебели",
      "qty": null,
      "unit": "",
      "costIncVat": 11039.17,
      "durationDaysPlanned": 5,
      "planStart": "2026-10-29",
      "planEnd": "2026-11-02",
      "actualStart": null,
      "actualEnd": null
    },
    {
      "id": "10",
      "section": "cleaning",
      "stage": "ST4",
      "name": "Уборка после работ",
      "qty": null,
      "unit": "",
      "costIncVat": 4101.49,
      "durationDaysPlanned": 3,
      "planStart": "2026-11-03",
      "planEnd": "2026-11-05",
      "actualStart": null,
      "actualEnd": null
    }
  ]
}